odoo/addons/product_stock_state/README.rst
odoo/addons/product_stock_state/__init__.py
odoo/addons/product_stock_state/__manifest__.py
odoo/addons/product_stock_state/data/data.xml
odoo/addons/product_stock_state/demo/product_category.xml
odoo/addons/product_stock_state/demo/product_product.xml
odoo/addons/product_stock_state/demo/res_groups.xml
odoo/addons/product_stock_state/i18n/ca.po
odoo/addons/product_stock_state/i18n/es.po
odoo/addons/product_stock_state/i18n/fr.po
odoo/addons/product_stock_state/i18n/it.po
odoo/addons/product_stock_state/i18n/nl.po
odoo/addons/product_stock_state/i18n/product_stock_state.pot
odoo/addons/product_stock_state/models/__init__.py
odoo/addons/product_stock_state/models/product_category.py
odoo/addons/product_stock_state/models/product_product.py
odoo/addons/product_stock_state/models/product_template.py
odoo/addons/product_stock_state/models/res_company.py
odoo/addons/product_stock_state/models/res_config_settings.py
odoo/addons/product_stock_state/readme/CONFIGURE.rst
odoo/addons/product_stock_state/readme/CONTRIBUTORS.rst
odoo/addons/product_stock_state/readme/CREDITS.rst
odoo/addons/product_stock_state/readme/DESCRIPTION.rst
odoo/addons/product_stock_state/readme/USAGE.rst
odoo/addons/product_stock_state/security/res_groups.xml
odoo/addons/product_stock_state/static/description/icon.png
odoo/addons/product_stock_state/static/description/index.html
odoo/addons/product_stock_state/static/description/product_product_tree.png
odoo/addons/product_stock_state/tests/__init__.py
odoo/addons/product_stock_state/tests/test_product_stock_state.py
odoo/addons/product_stock_state/views/product_category_view.xml
odoo/addons/product_stock_state/views/product_product_view.xml
odoo/addons/product_stock_state/views/product_template_view.xml
odoo/addons/product_stock_state/views/res_company_view.xml
odoo/addons/product_stock_state/views/res_config_settings_view.xml
odoo13_addon_product_stock_state-13.0.1.0.1.dev18.dist-info/METADATA
odoo13_addon_product_stock_state-13.0.1.0.1.dev18.dist-info/WHEEL
odoo13_addon_product_stock_state-13.0.1.0.1.dev18.dist-info/top_level.txt
odoo13_addon_product_stock_state-13.0.1.0.1.dev18.dist-info/RECORD
